ArabicTextNormalization/ArabbicTextNormalzation.py
ArabicTextNormalization/__init__.py
ArabicTextNormalization-0.0.2.dist-info/LICENSE
ArabicTextNormalization-0.0.2.dist-info/METADATA
ArabicTextNormalization-0.0.2.dist-info/WHEEL
ArabicTextNormalization-0.0.2.dist-info/top_level.txt
ArabicTextNormalization-0.0.2.dist-info/RECORD
