Metadata-Version: 2.1
Name: ArabicTextNormalization
Version: 0.0.2
Summary: ArabicTextNormalization
Home-page: UNKNOWN
Author: Yousif Ahmed Alhaj
Author-email: yalhag@gmail.com
License: UNKNOWN
Keywords: python,Arabic text preprocessing,Arabic text classification,Arabic text Normalization,Arabic sentiment ana;ysis
Platform: UNKNOWN
Classifier: Development Status :: 1 - Planning
Classifier: Intended Audience :: Developers
Classifier: Programming Language :: Python :: 3
Classifier: Operating System :: Unix
Classifier: Operating System :: MacOS :: MacOS X
Classifier: Operating System :: Microsoft :: Windows
License-File: LICENSE
